{"id": "game_003", "date": "2026-05-08", "time": "VEN 8 MAI", "home_team": "Olympiques DR M13", "away_team": "Tigres DR M13", "home_score": 2, "away_score": 3, "status": "FINAL", "tournament_day": 1, "location": "Complexe Sportif Thibault GM (Cadillac)", "game_number": "DRMS-003", "boxscore": {"teams": [{"id": "olympiques_m13", "name": "Olympiques DR M13", "logoUrl": null}, {"id": "tigres_m13", "name": "Tigres DR M13", "logoUrl": null}], "goals": [{"time": "1:21", "period": 1, "team": "tigres_m13", "player_name": "ALEXIS MAHEUX", "player_number": 7, "assists": [{"player_name": "CHARLES PELLETIER", "player_number": 12}]}, {"time": "7:20", "period": 1, "team": "olympiques_m13", "player_name": "FLORENT LITALIEN", "player_number": 7, "assists": [{"player_name": "ARTHUR POULIOT", "player_number": 11}, {"player_name": "NATHAN GADNON", "player_number": 5}]}, {"time": "11:48", "period": 1, "team": "tigres_m13", "player_name": "EMILE LEBLANC", "player_number": 14, "assists": [{"player_name": "MATT LEMIEUX", "player_number": 9}]}, {"time": "2:09", "period": 2, "team": "tigres_m13", "player_name": "CHARLES-OLIVIER DESBIENS", "player_number": 17, "assists": [{"player_name": "MILAN DERASPE", "player_number": 3}, {"player_name": "KYLE NOEL", "player_number": 2}]}, {"time": "14:10", "period": 2, "team": "olympiques_m13", "player_name": "EDOUARD BOUDREAULT", "player_number": 3, "assists": [{"player_name": "NOAM PATENAUD", "player_number": 2}, {"player_name": "ISAAK GAUTHIER", "player_number": 14}]}], "penalties": [], "roster": []}}